AnIntroductionToElm/README.md
AnIntroductionToElm/__init__.py
AnIntroductionToElm/__main__.py
AnIntroductionToElm/file.epub
AnIntroductionToElm/index.html
AnIntroductionToElm/css/__init__.py
AnIntroductionToElm/css/annotations.css
AnIntroductionToElm/css/main.css
AnIntroductionToElm/css/normalize.css
AnIntroductionToElm/css/popup.css
AnIntroductionToElm/font/__init__.py
AnIntroductionToElm/font/fontello.eot
AnIntroductionToElm/font/fontello.svg
AnIntroductionToElm/font/fontello.ttf
AnIntroductionToElm/font/fontello.woff
AnIntroductionToElm/img/__init__.py
AnIntroductionToElm/img/annotator-glyph-sprite.png
AnIntroductionToElm/img/annotator-icon-sprite.png
AnIntroductionToElm/img/apple-touch-icon.png
AnIntroductionToElm/img/cancelfullscreen.png
AnIntroductionToElm/img/close.png
AnIntroductionToElm/img/fullscreen.png
AnIntroductionToElm/img/loader.gif
AnIntroductionToElm/img/menu-icon.png
AnIntroductionToElm/img/save.png
AnIntroductionToElm/img/saved.png
AnIntroductionToElm/img/settings-s.png
AnIntroductionToElm/img/settings.png
AnIntroductionToElm/img/star.png
AnIntroductionToElm/js/__init__.py
AnIntroductionToElm/js/epub.js
AnIntroductionToElm/js/epub.min.js
AnIntroductionToElm/js/epub.min.map
AnIntroductionToElm/js/hooks.min.js
AnIntroductionToElm/js/hooks.min.map
AnIntroductionToElm/js/reader.js
AnIntroductionToElm/js/reader.js.map
AnIntroductionToElm/js/reader.min.js
AnIntroductionToElm/js/reader.min.map
AnIntroductionToElm/js/hooks/__init__.py
AnIntroductionToElm/js/hooks/extensions/__init__.py
AnIntroductionToElm/js/hooks/extensions/highlight.js
AnIntroductionToElm/js/libs/__init__.py
AnIntroductionToElm/js/libs/jquery.min.js
AnIntroductionToElm/js/libs/localforage.min.js
AnIntroductionToElm/js/libs/screenfull.js
AnIntroductionToElm/js/libs/screenfull.min.js
AnIntroductionToElm/js/libs/zip.min.js
AnIntroductionToElm/js/plugins/__init__.py
AnIntroductionToElm/js/plugins/hypothesis.js
AnIntroductionToElm/js/plugins/search.js
an_introduction_to_elm-2024.3.2.0.dist-info/METADATA
an_introduction_to_elm-2024.3.2.0.dist-info/WHEEL
an_introduction_to_elm-2024.3.2.0.dist-info/entry_points.txt
an_introduction_to_elm-2024.3.2.0.dist-info/top_level.txt
an_introduction_to_elm-2024.3.2.0.dist-info/RECORD
